ikakao/__init__.py
ikakao/utils.py
ikakao/skill/__init__.py
ikakao/skill/components.py
ikakao/skill/exceptions.py
ikakao/skill/response.py
ikakao/skill/serializable.py
ikakao/skill/template.py
ikakao-0.1.0.dist-info/METADATA
ikakao-0.1.0.dist-info/WHEEL
ikakao-0.1.0.dist-info/top_level.txt
ikakao-0.1.0.dist-info/RECORD
