Metadata-Version: 2.1
Name: ikakao
Version: 0.1.0
Summary: Kakao i Open Builder SDK
Home-page: https://github.com/hallazzang/ikakao
Author: Hanjun Kim
Author-email: hallazzang@gmail.com
License: UNKNOWN
Platform: UNKNOWN
Classifier: Programming Language :: Python
Requires-Python: >=3.6
